kicad_sch_api/__init__.py
kicad_sch_api/cli.py
kicad_sch_api/py.typed
kicad_sch_api/cli/__init__.py
kicad_sch_api/cli/base.py
kicad_sch_api/cli/bom.py
kicad_sch_api/cli/demo.py
kicad_sch_api/cli/erc.py
kicad_sch_api/cli/export_docs.py
kicad_sch_api/cli/find_libraries.py
kicad_sch_api/cli/kicad_to_python.py
kicad_sch_api/cli/netlist.py
kicad_sch_api/cli/setup_claude.py
kicad_sch_api/cli/types.py
kicad_sch_api/collections/__init__.py
kicad_sch_api/collections/base.py
kicad_sch_api/collections/bus_entries.py
kicad_sch_api/collections/components.py
kicad_sch_api/collections/junctions.py
kicad_sch_api/collections/labels.py
kicad_sch_api/collections/wires.py
kicad_sch_api/core/__init__.py
kicad_sch_api/core/component_bounds.py
kicad_sch_api/core/components.py
kicad_sch_api/core/config.py
kicad_sch_api/core/connectivity.py
kicad_sch_api/core/exceptions.py
kicad_sch_api/core/formatter.py
kicad_sch_api/core/geometry.py
kicad_sch_api/core/ic_manager.py
kicad_sch_api/core/junctions.py
kicad_sch_api/core/labels.py
kicad_sch_api/core/multi_unit.py
kicad_sch_api/core/nets.py
kicad_sch_api/core/no_connects.py
kicad_sch_api/core/parser.py
kicad_sch_api/core/parsing_utils.py
kicad_sch_api/core/pin_utils.py
kicad_sch_api/core/property_positioning.py
kicad_sch_api/core/schematic.py
kicad_sch_api/core/texts.py
kicad_sch_api/core/types.py
kicad_sch_api/core/wires.py
kicad_sch_api/core/collections/__init__.py
kicad_sch_api/core/collections/base.py
kicad_sch_api/core/factories/__init__.py
kicad_sch_api/core/factories/element_factory.py
kicad_sch_api/core/managers/__init__.py
kicad_sch_api/core/managers/base.py
kicad_sch_api/core/managers/file_io.py
kicad_sch_api/core/managers/format_sync.py
kicad_sch_api/core/managers/graphics.py
kicad_sch_api/core/managers/hierarchy.py
kicad_sch_api/core/managers/metadata.py
kicad_sch_api/core/managers/sheet.py
kicad_sch_api/core/managers/text_elements.py
kicad_sch_api/core/managers/validation.py
kicad_sch_api/core/managers/wire.py
kicad_sch_api-0.5.5.dist-info/licenses/LICENSE
kicad_sch_api-0.5.5.dist-info/METADATA
kicad_sch_api-0.5.5.dist-info/WHEEL
kicad_sch_api-0.5.5.dist-info/entry_points.txt
kicad_sch_api-0.5.5.dist-info/top_level.txt
kicad_sch_api-0.5.5.dist-info/RECORD
