Metadata-Version: 2.4
Name: kicad-sch-api
Version: 0.5.5
Summary: Professional KiCAD schematic manipulation library with exact format preservation
Author-email: Circuit-Synth <shane@circuit-synth.com>
Maintainer-email: Circuit-Synth <shane@circuit-synth.com>
License-Expression: MIT
Project-URL: Homepage, https://github.com/circuit-synth/kicad-sch-api
Project-URL: Documentation, https://kicad-sch-api.readthedocs.io/
Project-URL: Repository, https://github.com/circuit-synth/kicad-sch-api.git
Project-URL: Bug Reports, https://github.com/circuit-synth/kicad-sch-api/issues
Project-URL: Changelog, https://github.com/circuit-synth/kicad-sch-api/blob/main/CHANGELOG.md
Keywords: kicad,schematic,eda,electronics,circuit-design,ai,automation,pcb
Classifier: Development Status :: 4 - Beta
Classifier: Intended Audience :: Developers
Classifier: Intended Audience :: Science/Research
Classifier: Topic :: Scientific/Engineering :: Electronic Design Automation (EDA)
Classifier: Programming Language :: Python :: 3
Classifier: Programming Language :: Python :: 3.10
Classifier: Programming Language :: Python :: 3.11
Classifier: Programming Language :: Python :: 3.12
Classifier: Operating System :: OS Independent
Requires-Python: >=3.10
License-File: LICENSE
Requires-Dist: sexpdata>=0.0.3
Requires-Dist: typing-extensions>=4.0.0; python_version < "3.11"
Requires-Dist: pydantic>=2.0.0
Requires-Dist: mcp>=1.10.0
Requires-Dist: fastmcp>=0.2.0
Requires-Dist: jinja2>=3.0.0
Provides-Extra: dev
Requires-Dist: pytest>=7.0.0; extra == "dev"
Requires-Dist: pytest-cov>=4.0.0; extra == "dev"
Requires-Dist: pytest-xdist>=3.0.0; extra == "dev"
Requires-Dist: pytest-asyncio>=0.21.0; extra == "dev"
Requires-Dist: black>=22.0.0; extra == "dev"
Requires-Dist: isort>=5.0.0; extra == "dev"
Requires-Dist: flake8>=4.0.0; extra == "dev"
Requires-Dist: mypy>=1.0.0; extra == "dev"
Requires-Dist: pre-commit>=3.0.0; extra == "dev"
Provides-Extra: docs
Requires-Dist: sphinx>=5.0.0; extra == "docs"
Requires-Dist: sphinx-rtd-theme>=1.0.0; extra == "docs"
Requires-Dist: myst-parser>=0.18.0; extra == "docs"
Dynamic: license-file
